yamper/__init__.py
yamper/cli.py
yamper/core.py
yamper/common/__init__.py
yamper/common/pattern.py
yamper/common/token_type.py
yamper/lexer/__init__.py
yamper/lexer/lexer.py
yamper/lexer/token.py
yamper/parser/__init__.py
yamper/parser/clean_emoji_data.py
yamper/parser/emoji_dict.py
yamper/parser/inline_processor.py
yamper/parser/parser.py
yamper/renderer/__init__.py
yamper/renderer/node.py
yamper/renderer/renderer.py
yamper/templates/plain.html
yamper/templates/standard-dark.html
yamper/templates/standard-light.html
yamper-0.1.0.dist-info/METADATA
yamper-0.1.0.dist-info/WHEEL
yamper-0.1.0.dist-info/entry_points.txt
yamper-0.1.0.dist-info/licenses/LICENSE
yamper-0.1.0.dist-info/RECORD
