Metadata-Version: 2.3
Name: yamper
Version: 0.1.0
Summary: A Markdown to HTML converter
Project-URL: Homepage, https://github.com/useDeep/yamper
Project-URL: Issues, https://github.com/useDeep/yamper/issues
Author-email: Deepak <hey.usedeep@email.com>
License-File: LICENSE
Classifier: License :: OSI Approved :: GNU General Public License v3 (GPLv3)
Classifier: Operating System :: OS Independent
Classifier: Programming Language :: Python :: 3
Requires-Python: >=3.8
